vid2pdf/__init__.py
vid2pdf/dialog.py
vid2pdf/vid2pdf.py
vid2pdf-1.2.0.dist-info/licenses/LICENSE
vid2pdf-1.2.0.dist-info/WHEEL
vid2pdf-1.2.0.dist-info/entry_points.txt
vid2pdf-1.2.0.dist-info/METADATA
vid2pdf-1.2.0.dist-info/RECORD
