Metadata-Version: 2.4
Name: vid2pdf
Version: 1.2.0
Summary: Convert a video file into PDF image series
Author: sco1
Author-email: sco1 <sco1.git@gmail.com>
License-Expression: MIT
License-File: LICENSE
Classifier: Development Status :: 4 - Beta
Classifier: Intended Audience :: Developers
Classifier: Operating System :: OS Independent
Classifier: Programming Language :: Python :: 3 :: Only
Classifier: Programming Language :: Python :: 3.11
Classifier: Programming Language :: Python :: 3.12
Classifier: Programming Language :: Python :: 3.13
Classifier: Programming Language :: Python :: 3.14
Classifier: Typing :: Typed
Requires-Dist: ffmpy~=0.5
Requires-Dist: pillow~=11.0
Requires-Dist: python-dotenv~=1.1
Requires-Dist: tqdm~=4.67
Requires-Dist: typer-slim~=0.17
Requires-Dist: nuitka~=2.7 ; extra == 'build'
Requires-Python: >=3.11
Project-URL: Changelog, https://github.com/sco1/vid2pdf/blob/main/CHANGELOG.md
Project-URL: Documentation, https://github.com/sco1/vid2pdf/blob/main/README.md
Project-URL: Homepage, https://github.com/sco1/
Project-URL: Issues, https://github.com/sco1/vid2pdf/issues
Project-URL: Repository, https://github.com/sco1/vid2pdf.git
Provides-Extra: build
